sphinx_mdolab_theme/__init__.py
sphinx_mdolab_theme/config.py
sphinx_mdolab_theme/theme.conf
sphinx_mdolab_theme/ext/__init__.py
sphinx_mdolab_theme/ext/embed_bibtex.py
sphinx_mdolab_theme/ext/embed_code.py
sphinx_mdolab_theme/ext/embed_compare.py
sphinx_mdolab_theme/ext/embed_n2.py
sphinx_mdolab_theme/ext/embed_shell_cmd.py
sphinx_mdolab_theme/ext/optionslist.py
sphinx_mdolab_theme/ext/optionstable.py
sphinx_mdolab_theme/ext/tags.py
sphinx_mdolab_theme/static/MDO_Lab_logo_RTD.png
sphinx_mdolab_theme/static/theme_overrides.css
sphinx_mdolab_theme/utils/__init__.py
sphinx_mdolab_theme/utils/docutil.py
sphinx_mdolab_theme/utils/general_utils.py
sphinx_mdolab_theme/utils/run_sub.py
sphinx_mdolab_theme-1.4.4.dist-info/METADATA
sphinx_mdolab_theme-1.4.4.dist-info/WHEEL
sphinx_mdolab_theme-1.4.4.dist-info/entry_points.txt
sphinx_mdolab_theme-1.4.4.dist-info/top_level.txt
sphinx_mdolab_theme-1.4.4.dist-info/RECORD
