Metadata-Version: 2.1
Name: sphinx-mdolab-theme
Version: 1.4.4
Summary: MDO Lab sphinx theme
Home-page: https://github.com/mdolab/sphinx_mdolab_theme
Author: MDO Lab
Author-email: mdolabbuildbot@gmail.com
License: MIT
Keywords: SPHINX,THEME,MDOLAB
Platform: UNKNOWN
Classifier: Development Status :: 5 - Production/Stable
Classifier: Intended Audience :: Developers
Classifier: Topic :: Software Development :: Build Tools
Classifier: License :: OSI Approved :: MIT License
Classifier: Programming Language :: Python :: 3
Requires-Dist: sphinx>=3.0
Requires-Dist: sphinx-rtd-theme>=0.5
Requires-Dist: pyyaml
Requires-Dist: numpydoc
Requires-Dist: sphinx-prompt
Requires-Dist: sphinx-copybutton
Requires-Dist: sphinxcontrib-autoprogram
Requires-Dist: sphinxcontrib-bibtex
Requires-Dist: sphinx-tabs
Requires-Dist: redbaron
Requires-Dist: numpy
